sarscov2formatter/__init__.py
sarscov2formatter/cli.py
sarscov2formatter-0.5.3.dist-info/LICENSE
sarscov2formatter-0.5.3.dist-info/METADATA
sarscov2formatter-0.5.3.dist-info/WHEEL
sarscov2formatter-0.5.3.dist-info/entry_points.txt
sarscov2formatter-0.5.3.dist-info/top_level.txt
sarscov2formatter-0.5.3.dist-info/RECORD
